cvx/bson/__init__.py
cvx/bson/dataclass.py
cvx/bson/file.py
cvx/bson/io.py
cvx/json/__init__.py
cvx/json/file.py
cvx/json/numpyencoder.py
cvxbson-0.2.0.dist-info/METADATA
cvxbson-0.2.0.dist-info/WHEEL
cvxbson-0.2.0.dist-info/licenses/LICENSE
cvxbson-0.2.0.dist-info/RECORD
