Metadata-Version: 2.4
Name: cvxbson
Version: 0.2.0
Summary: Dealing with json and bson files
Project-URL: repository, https://github.com/cvxgrp/cvxbson
Author-email: Thomas Schmelzer <thomas.schmelzer@gmail.com>
License-File: LICENSE
Requires-Python: >=3.10
Requires-Dist: bson>=0.5.10
Requires-Dist: numpy>=2
Requires-Dist: pandas>=2
Requires-Dist: polars>=1.16.0
Requires-Dist: pyarrow>=18.1.0
Provides-Extra: dev
Requires-Dist: marimo~=0.14.17; extra == 'dev'
Requires-Dist: pre-commit>=4.2.0; extra == 'dev'
Requires-Dist: pytest-cov>=6.0.0; extra == 'dev'
Requires-Dist: pytest>=8.3.3; extra == 'dev'
